{
  "label": "game_2026_03_19_-_17_50_43",
  "mode": "game",
  "save_id": "20260319T205045486828Z-game-ai-ui-v2-game-2026-03-19-17-50-43",
  "saved_at": "2026-03-19T20:50:45.486828Z",
  "snapshot": {
    "active_action_feed": [
      {
        "action": "Destino definido",
        "color": "#ef4444",
        "createdAt": 1773953440869,
        "detail": "NYC | $ 270",
        "expiresAt": 1773953470869,
        "glow": "#f69393",
        "id": "1773953440869-e14e7e4a9d256",
        "playerId": "cpu-3",
        "playerName": "Jogador 3",
        "turnLabel": "Turno 26"
      },
      {
        "action": "Pedagio sorteado",
        "color": "#ef4444",
        "createdAt": 1773953440705,
        "detail": "USH",
        "expiresAt": 1773953470705,
        "glow": "#f69393",
        "id": "1773953440705-3c549df86a7578",
        "playerId": "cpu-3",
        "playerName": "Jogador 3",
        "turnLabel": "Turno 26"
      },
      {
        "action": "Porto comprado no destino",
        "color": "#ef4444",
        "createdAt": 1773953440166,
        "detail": "DAR por $ 330.",
        "expiresAt": 1773953470166,
        "glow": "#f69393",
        "id": "1773953440166-bcc0498aafa7e8",
        "playerId": "cpu-3",
        "playerName": "Jogador 3",
        "turnLabel": "Turno 26"
      },
      {
        "action": "Recebeu estadia",
        "color": "#2563eb",
        "createdAt": 1773953439769,
        "detail": "JED: $ 10 de Jogador 2.",
        "expiresAt": 1773953469769,
        "glow": "#81a5f3",
        "id": "1773953439769-c41e287be5d1e",
        "playerId": "human",
        "playerName": "Minha Companhia",
        "turnLabel": "Turno 26"
      },
      {
        "action": "Estadia ao dono",
        "color": "#22c55e",
        "createdAt": 1773953439760,
        "detail": "JED: $ 10 para Minha Companhia.",
        "expiresAt": 1773953469760,
        "glow": "#7fdda2",
        "id": "1773953439760-a205dc26a3cb7",
        "playerId": "cpu-2",
        "playerName": "Jogador 2",
        "turnLabel": "Turno 26"
      },
      {
        "action": "Negociacao recusada",
        "color": "#2563eb",
        "createdAt": 1773953439724,
        "detail": "JED ficou com voce.",
        "expiresAt": 1773953469724,
        "glow": "#81a5f3",
        "id": "1773953439724-dfcd438c4f9e4",
        "playerId": "human",
        "playerName": "Minha Companhia",
        "turnLabel": "Turno 26"
      },
      {
        "action": "Negociacao recusada",
        "color": "#22c55e",
        "createdAt": 1773953439715,
        "detail": "JED ficou com Minha Companhia: Sem acordo. o porto JED continua na sua companhia.",
        "expiresAt": 1773953469715,
        "glow": "#7fdda2",
        "id": "1773953439715-ecb536267680b8",
        "playerId": "cpu-2",
        "playerName": "Jogador 2",
        "turnLabel": "Turno 26"
      }
    ],
    "ai": {
      "aiDifficultyId": "normal",
      "aiProfileModeId": "balanced",
      "stageId": "stage8_profile_setup",
      "stageLabel": "Perfis, cupons e caixa"
    },
    "chance_deck": {
      "discard_pile": [
        "baleias",
        "nova_especie",
        "ataque_submarino",
        "manutencao_total",
        "maelstrom",
        "desastre_maritimo",
        "gasolina_livre",
        "sardinhas",
        "atlantida",
        "nautilus",
        "piratas",
        "motim",
        "reliquias",
        "bermudas",
        "vazamento",
        "corrente_a_favor",
        "atraso_de_entrega",
        "alfandega",
        "pedagio_extra",
        "lucro_extra",
        "banco_de_gelo",
        "iceberg",
        "pedagio_livre",
        "sabotagem",
        "vento_a_favor",
        "aposta",
        "greve",
        "quebra_de_contrato"
      ],
      "draw_pile": [
        "tempestade",
        "time_campeao",
        "contra_o_monopolio",
        "atalho",
        "naufrago",
        "lula_gigante",
        "porto_livre"
      ],
      "held_card_ids": [
        "contrato_cancelado",
        "prazo_estendido",
        "viagem_de_graca",
        "mudanca_de_rota"
      ]
    },
    "mortgaged_property_codes": [],
    "players": [
      {
        "active_contract": {
          "base_freight_value": 28,
          "cargo_label": "Granel",
          "completed": false,
          "deadline_label": "2 / 4",
          "deadline_progress": "2/4",
          "destination": "REC",
          "distance_label": "Distancia 7",
          "distance_value": 7,
          "free_fuel_for_contract": false,
          "freight_label": "Frete $ 28",
          "freight_value": 28,
          "mandatory_toll": "USH",
          "note": "Minha Companhia parou em Abastecimento 25 e pagou $ 25 ao banco.",
          "origin": "MAZ",
          "origin_monopoly": false,
          "origin_owned": false,
          "rounds_elapsed": 2,
          "route_stage": "to_toll",
          "settlement_adjustment": 0,
          "settlement_value": 28,
          "target_rounds": 4,
          "toll_passed": false,
          "toll_requirement_waived": false
        },
        "active_permission_id": "bulk",
        "active_permission_label": "Granel",
        "bankrupt": false,
        "board_node_id": "fuel-045",
        "cash": 1274,
        "cash_display": "$ 1.274",
        "color_hex": "#2563eb",
        "color_id": "blue",
        "coupons": [],
        "id": "human",
        "is_human": true,
        "last_roll": [
          1,
          3
        ],
        "location_code": null,
        "location_label": "Abastecimento 25",
        "monopoly_regions": [],
        "name": "Minha Companhia",
        "needs_new_contract": false,
        "permissions": [
          {
            "accent": "#17C51A",
            "id": "bulk",
            "kind": "bulk",
            "mortgaged": false,
            "purchase_price": 2000,
            "text": "#FFFFFF",
            "title": "Granel"
          }
        ],
        "property_codes": [
          "REC",
          "MUM",
          "TOK",
          "JED"
        ],
        "ship_type": "bulk",
        "ship_type_label": "Granel",
        "skip_turns": 0,
        "status_label": "abasteceu $ 25"
      },
      {
        "active_contract": {
          "base_freight_value": 168,
          "cargo_label": "Petr\u00f3leo",
          "completed": true,
          "deadline_label": "3 / 4",
          "deadline_progress": "3/4",
          "destination": "CAR",
          "distance_label": "Distancia 14",
          "distance_value": 14,
          "free_fuel_for_contract": false,
          "freight_label": "Frete $ 168",
          "freight_value": 218,
          "mandatory_toll": "SUZ",
          "note": "O navio chegou em CAR depois de passar por SUZ e recebeu $ 218 ($ 168 + bonus $ 50).",
          "origin": "JED",
          "origin_monopoly": false,
          "origin_owned": false,
          "rounds_elapsed": 3,
          "route_stage": "arrived",
          "settlement_adjustment": 50,
          "settlement_value": 218,
          "target_rounds": 4,
          "toll_passed": true,
          "toll_requirement_waived": false
        },
        "active_permission_id": "oil",
        "active_permission_label": "Petr\u00f3leo",
        "ai": {
          "archetype_id": "balanced_trader",
          "manual_profile": true,
          "profile_id": "balanced_trader",
          "profile_label": "Equilibrado",
          "profile_overrides": {
            "metadata": {
              "archetype_id": "balanced_trader",
              "negotiation_preset_id": "protetor",
              "personality_preset_id": "patrimonialista",
              "setup_archetype_id": "balanced_trader",
              "setup_customized": true,
              "skill_preset_id": "elite",
              "table_preset_id": "stage6_profile_table",
              "vision_preset_id": "foco_contrato"
            },
            "negotiation": {
              "buy_openness": 0.1,
              "desperation_discount": 0.2,
              "discount_tolerance": 0.1,
              "premium_tolerance": 0.7,
              "sell_openness": 0.1,
              "strategic_lock": 0.8
            },
            "personality": {
              "asset_attachment": 0.8,
              "cash_reserve_ratio": 0.3,
              "coupon_patience": 0.6,
              "description": "Mantem postura media entre protecao, ousadia e paciencia. Serve como referencia central para calibrar comportamento geral da mesa.",
              "id": "equilibrado",
              "impulsiveness": 0.2,
              "label": "Temperado",
              "risk_tolerance": 0.3
            },
            "skill": {
              "combo_awareness": 0.9,
              "evaluation_noise": 0,
              "foresight": 0.9,
              "liquidity_discipline": 0.9,
              "timing_quality": 0.9
            },
            "vision": {
              "planning_horizon_turns": 0.3,
              "weight_monopoly": 0.4,
              "weight_origin_bonus": 1,
              "weight_permission": 0.5,
              "weight_port": 0.8,
              "weight_toll": 0.1
            }
          },
          "skill": {
            "combo_awareness": 0.9,
            "description": "Perfil confiavel para jogo padrao. Comete menos oscilacoes, respeita melhor caixa e enxerga combinacoes basicas com consistencia.",
            "evaluation_noise": 0,
            "foresight": 0.9,
            "id": "solido",
            "label": "Solido",
            "liquidity_discipline": 0.9,
            "timing_quality": 0.9
          },
          "skill_preset_id": "elite"
        },
        "bankrupt": false,
        "board_node_id": "car",
        "cash": 1048,
        "cash_display": "$ 1.048",
        "color_hex": "#eab308",
        "color_id": "yellow",
        "coupons": [
          {
            "acquired_turn": 9,
            "expires_after_turns": 100,
            "kind": "extended_contract_deadline",
            "label": "Prazo Estendido",
            "source_card_id": "prazo_estendido"
          }
        ],
        "id": "cpu-1",
        "is_human": false,
        "last_roll": [
          3,
          4
        ],
        "location_code": "CAR",
        "location_label": "CAR",
        "monopoly_regions": [],
        "name": "Jogador 1",
        "needs_new_contract": true,
        "permissions": [
          {
            "accent": "#4C4C4C",
            "id": "oil",
            "kind": "oil",
            "mortgaged": false,
            "purchase_price": 2000,
            "text": "#FFFFFF",
            "title": "Petr\u00f3leo"
          }
        ],
        "property_codes": [
          "MAZ",
          "CAR",
          "NYC",
          "GUA"
        ],
        "ship_type": "oil",
        "ship_type_label": "Petr\u00f3leo",
        "skip_turns": 0,
        "status_label": "recebeu $ 218"
      },
      {
        "active_contract": {
          "base_freight_value": 70,
          "cargo_label": "Autom\u00f3veis",
          "completed": false,
          "deadline_label": "1 / 4",
          "deadline_progress": "1/4",
          "destination": "SYD",
          "distance_label": "Distancia 14",
          "distance_value": 14,
          "free_fuel_for_contract": false,
          "freight_label": "Frete $ 70",
          "freight_value": 70,
          "mandatory_toll": "SUZ",
          "note": "Jogador 2 pagou $ 10 a Minha Companhia em JED.",
          "origin": "JED",
          "origin_monopoly": false,
          "origin_owned": false,
          "rounds_elapsed": 1,
          "route_stage": "to_destination",
          "settlement_adjustment": 0,
          "settlement_value": 70,
          "target_rounds": 4,
          "toll_passed": true,
          "toll_requirement_waived": false
        },
        "active_permission_id": "cars",
        "active_permission_label": "Autom\u00f3veis",
        "ai": {
          "archetype_id": "balanced_trader",
          "manual_profile": true,
          "profile_id": "balanced_trader",
          "profile_label": "Equilibrado",
          "profile_overrides": {
            "metadata": {
              "archetype_id": "balanced_trader",
              "negotiation_preset_id": "protetor",
              "personality_preset_id": "patrimonialista",
              "setup_archetype_id": "balanced_trader",
              "setup_customized": true,
              "skill_preset_id": "elite",
              "table_preset_id": "stage6_profile_table",
              "vision_preset_id": "foco_portos"
            },
            "negotiation": {
              "buy_openness": 0.1,
              "desperation_discount": 0.2,
              "discount_tolerance": 0.1,
              "premium_tolerance": 0.7,
              "sell_openness": 0.1,
              "strategic_lock": 0.8
            },
            "personality": {
              "asset_attachment": 0.8,
              "cash_reserve_ratio": 0.3,
              "coupon_patience": 0.6,
              "description": "Mantem postura media entre protecao, ousadia e paciencia. Serve como referencia central para calibrar comportamento geral da mesa.",
              "id": "equilibrado",
              "impulsiveness": 0.2,
              "label": "Temperado",
              "risk_tolerance": 0.3
            },
            "skill": {
              "combo_awareness": 0.9,
              "evaluation_noise": 0,
              "foresight": 0.9,
              "liquidity_discipline": 0.9,
              "timing_quality": 0.9
            },
            "vision": {
              "planning_horizon_turns": 0.1,
              "weight_monopoly": 0.2,
              "weight_origin_bonus": 0.9,
              "weight_permission": 0.3,
              "weight_port": 0.9,
              "weight_toll": 0.1
            }
          },
          "skill": {
            "combo_awareness": 0.9,
            "description": "Perfil confiavel para jogo padrao. Comete menos oscilacoes, respeita melhor caixa e enxerga combinacoes basicas com consistencia.",
            "evaluation_noise": 0,
            "foresight": 0.9,
            "id": "solido",
            "label": "Solido",
            "liquidity_discipline": 0.9,
            "timing_quality": 0.9
          },
          "skill_preset_id": "elite"
        },
        "bankrupt": false,
        "board_node_id": "jed",
        "cash": 885,
        "cash_display": "$ 885",
        "color_hex": "#22c55e",
        "color_id": "green",
        "coupons": [
          {
            "acquired_turn": 7,
            "expires_after_turns": 100,
            "kind": "cancel_contract",
            "label": "Contrato Cancelado",
            "source_card_id": "contrato_cancelado"
          }
        ],
        "id": "cpu-2",
        "is_human": false,
        "last_roll": [
          1,
          3
        ],
        "location_code": "JED",
        "location_label": "JED",
        "monopoly_regions": [],
        "name": "Jogador 2",
        "needs_new_contract": false,
        "permissions": [
          {
            "accent": "#A9C4E4",
            "id": "cars",
            "kind": "cars",
            "mortgaged": false,
            "purchase_price": 2000,
            "text": "#FFFFFF",
            "title": "Autom\u00f3veis"
          }
        ],
        "property_codes": [
          "REC",
          "LAG",
          "MAN",
          "VAL"
        ],
        "ship_type": "cars",
        "ship_type_label": "Autom\u00f3veis",
        "skip_turns": 0,
        "status_label": "pagou $ 10"
      },
      {
        "active_contract": {
          "base_freight_value": 270,
          "cargo_label": "G\u00e1s",
          "completed": false,
          "deadline_label": "1 / 4",
          "deadline_progress": "1/4",
          "destination": "NYC",
          "distance_label": "Distancia 15",
          "distance_value": 15,
          "free_fuel_for_contract": false,
          "freight_label": "Frete $ 270",
          "freight_value": 270,
          "mandatory_toll": "USH",
          "note": "Contrato: 15 x 6 x 3 = 270. Aplicado porto de partida comprado.",
          "origin": "DAR",
          "origin_monopoly": false,
          "origin_owned": true,
          "rounds_elapsed": 1,
          "route_stage": "to_toll",
          "settlement_adjustment": 0,
          "settlement_value": 270,
          "target_rounds": 4,
          "toll_passed": false,
          "toll_requirement_waived": false
        },
        "active_permission_id": "gas",
        "active_permission_label": "G\u00e1s",
        "ai": {
          "archetype_id": "balanced_trader",
          "manual_profile": true,
          "profile_id": "balanced_trader",
          "profile_label": "Equilibrado",
          "profile_overrides": {
            "metadata": {
              "archetype_id": "balanced_trader",
              "negotiation_preset_id": "protetor",
              "personality_preset_id": "patrimonialista",
              "setup_archetype_id": "balanced_trader",
              "setup_customized": true,
              "skill_preset_id": "elite",
              "table_preset_id": "stage6_profile_table",
              "vision_preset_id": "foco_malha"
            },
            "negotiation": {
              "buy_openness": 0.1,
              "desperation_discount": 0.2,
              "discount_tolerance": 0.1,
              "premium_tolerance": 0.7,
              "sell_openness": 0.1,
              "strategic_lock": 0.8
            },
            "personality": {
              "asset_attachment": 0.8,
              "cash_reserve_ratio": 0.3,
              "coupon_patience": 0.6,
              "description": "Mantem postura media entre protecao, ousadia e paciencia. Serve como referencia central para calibrar comportamento geral da mesa.",
              "id": "equilibrado",
              "impulsiveness": 0.2,
              "label": "Temperado",
              "risk_tolerance": 0.3
            },
            "skill": {
              "combo_awareness": 0.9,
              "evaluation_noise": 0,
              "foresight": 0.9,
              "liquidity_discipline": 0.9,
              "timing_quality": 0.9
            },
            "vision": {
              "planning_horizon_turns": 0.3,
              "weight_monopoly": 0.3,
              "weight_origin_bonus": 0.9,
              "weight_permission": 0.9,
              "weight_port": 0.7,
              "weight_toll": 0.1
            }
          },
          "skill": {
            "combo_awareness": 0.9,
            "description": "Perfil confiavel para jogo padrao. Comete menos oscilacoes, respeita melhor caixa e enxerga combinacoes basicas com consistencia.",
            "evaluation_noise": 0,
            "foresight": 0.9,
            "id": "solido",
            "label": "Solido",
            "liquidity_discipline": 0.9,
            "timing_quality": 0.9
          },
          "skill_preset_id": "elite"
        },
        "bankrupt": false,
        "board_node_id": "fuel-064",
        "cash": 2128,
        "cash_display": "$ 2.128",
        "color_hex": "#ef4444",
        "color_id": "red",
        "coupons": [
          {
            "acquired_turn": 15,
            "expires_after_turns": 100,
            "kind": "free_fuel_contract",
            "label": "Viagem de Gra\u00e7a",
            "source_card_id": "viagem_de_graca"
          },
          {
            "acquired_turn": 19,
            "expires_after_turns": 100,
            "kind": "reroute_same_value",
            "label": "Mudan\u00e7a de Rota",
            "source_card_id": "mudanca_de_rota"
          }
        ],
        "id": "cpu-3",
        "is_human": false,
        "last_roll": [
          5,
          1
        ],
        "location_code": null,
        "location_label": "Abastecimento 20",
        "monopoly_regions": [],
        "name": "Jogador 3",
        "needs_new_contract": false,
        "permissions": [
          {
            "accent": "#F2B400",
            "id": "gas",
            "kind": "gas",
            "mortgaged": false,
            "purchase_price": 2000,
            "text": "#FFFFFF",
            "title": "G\u00e1s"
          }
        ],
        "property_codes": [
          "SPE",
          "VAN",
          "JAK",
          "DAR"
        ],
        "ship_type": "gas",
        "ship_type_label": "G\u00e1s",
        "skip_turns": 0,
        "status_label": "novo contrato pronto"
      },
      {
        "active_contract": {
          "base_freight_value": 78,
          "cargo_label": "Cruzeiro",
          "completed": false,
          "deadline_label": "4 / 4",
          "deadline_progress": "4/4",
          "destination": "AUC",
          "distance_label": "Distancia 13",
          "distance_value": 13,
          "free_fuel_for_contract": false,
          "freight_label": "Frete $ 78",
          "freight_value": 78,
          "mandatory_toll": "SUZ",
          "note": "Jogador 4 pagou $ 10 ao banco em SRI.",
          "origin": "MAN",
          "origin_monopoly": false,
          "origin_owned": false,
          "rounds_elapsed": 4,
          "route_stage": "to_destination",
          "settlement_adjustment": 0,
          "settlement_value": 78,
          "target_rounds": 4,
          "toll_passed": true,
          "toll_requirement_waived": false
        },
        "active_permission_id": "cruise",
        "active_permission_label": "Cruzeiro",
        "ai": {
          "archetype_id": "balanced_trader",
          "manual_profile": true,
          "profile_id": "balanced_trader",
          "profile_label": "Equilibrado",
          "profile_overrides": {
            "metadata": {
              "archetype_id": "balanced_trader",
              "negotiation_preset_id": "protetor",
              "personality_preset_id": "patrimonialista",
              "setup_archetype_id": "balanced_trader",
              "setup_customized": true,
              "skill_preset_id": "elite",
              "table_preset_id": "stage6_profile_table",
              "vision_preset_id": "foco_pedagios"
            },
            "negotiation": {
              "buy_openness": 0.1,
              "desperation_discount": 0.2,
              "discount_tolerance": 0.1,
              "premium_tolerance": 0.7,
              "sell_openness": 0.1,
              "strategic_lock": 0.8
            },
            "personality": {
              "asset_attachment": 0.8,
              "cash_reserve_ratio": 0.3,
              "coupon_patience": 0.6,
              "description": "Mantem postura media entre protecao, ousadia e paciencia. Serve como referencia central para calibrar comportamento geral da mesa.",
              "id": "equilibrado",
              "impulsiveness": 0.2,
              "label": "Temperado",
              "risk_tolerance": 0.3
            },
            "skill": {
              "combo_awareness": 0.9,
              "evaluation_noise": 0,
              "foresight": 0.9,
              "liquidity_discipline": 0.9,
              "timing_quality": 0.9
            },
            "vision": {
              "planning_horizon_turns": 0.5,
              "weight_monopoly": 0.2,
              "weight_origin_bonus": 0.2,
              "weight_permission": 0.3,
              "weight_port": 0.2,
              "weight_toll": 0.9
            }
          },
          "skill": {
            "combo_awareness": 0.9,
            "description": "Perfil confiavel para jogo padrao. Comete menos oscilacoes, respeita melhor caixa e enxerga combinacoes basicas com consistencia.",
            "evaluation_noise": 0,
            "foresight": 0.9,
            "id": "solido",
            "label": "Solido",
            "liquidity_discipline": 0.9,
            "timing_quality": 0.9
          },
          "skill_preset_id": "elite"
        },
        "bankrupt": false,
        "board_node_id": "sri",
        "cash": 1982,
        "cash_display": "$ 1.982",
        "color_hex": "#f97316",
        "color_id": "orange",
        "coupons": [],
        "id": "cpu-4",
        "is_human": false,
        "last_roll": [
          4,
          2
        ],
        "location_code": "SRI",
        "location_label": "SRI",
        "monopoly_regions": [],
        "name": "Jogador 4",
        "needs_new_contract": false,
        "permissions": [
          {
            "accent": "#D60A00",
            "id": "cruise",
            "kind": "cruise",
            "mortgaged": false,
            "purchase_price": 2000,
            "text": "#FFFFFF",
            "title": "Cruzeiro"
          }
        ],
        "property_codes": [],
        "ship_type": "cruise",
        "ship_type_label": "Cruzeiro",
        "skip_turns": 0,
        "status_label": "pagou $ 10"
      },
      {
        "active_contract": {
          "base_freight_value": 450,
          "cargo_label": "Petr\u00f3leo",
          "completed": false,
          "deadline_label": "1 / 4",
          "deadline_progress": "1/4",
          "destination": "NYC",
          "distance_label": "Distancia 10",
          "distance_value": 10,
          "free_fuel_for_contract": false,
          "freight_label": "Frete $ 450",
          "freight_value": 450,
          "mandatory_toll": "SUZ",
          "note": "Rev\u00e9s: Greve. Jogador 5 vai parar 1 rodada(s).",
          "origin": "RIO",
          "origin_monopoly": false,
          "origin_owned": true,
          "rounds_elapsed": 1,
          "route_stage": "to_toll",
          "settlement_adjustment": 0,
          "settlement_value": 450,
          "target_rounds": 4,
          "toll_passed": false,
          "toll_requirement_waived": false
        },
        "active_permission_id": "oil",
        "active_permission_label": "Petr\u00f3leo",
        "ai": {
          "archetype_id": "balanced_trader",
          "manual_profile": true,
          "profile_id": "balanced_trader",
          "profile_label": "Equilibrado",
          "profile_overrides": {
            "metadata": {
              "archetype_id": "balanced_trader",
              "negotiation_preset_id": "protetor",
              "personality_preset_id": "patrimonialista",
              "setup_archetype_id": "balanced_trader",
              "setup_customized": true,
              "skill_preset_id": "elite",
              "table_preset_id": "stage6_profile_table",
              "vision_preset_id": "foco_monopolio"
            },
            "negotiation": {
              "buy_openness": 0.1,
              "desperation_discount": 0.2,
              "discount_tolerance": 0.1,
              "premium_tolerance": 0.7,
              "sell_openness": 0.1,
              "strategic_lock": 0.8
            },
            "personality": {
              "asset_attachment": 0.8,
              "cash_reserve_ratio": 0.3,
              "coupon_patience": 0.6,
              "description": "Mantem postura media entre protecao, ousadia e paciencia. Serve como referencia central para calibrar comportamento geral da mesa.",
              "id": "equilibrado",
              "impulsiveness": 0.2,
              "label": "Temperado",
              "risk_tolerance": 0.3
            },
            "skill": {
              "combo_awareness": 0.9,
              "evaluation_noise": 0,
              "foresight": 0.9,
              "liquidity_discipline": 0.9,
              "timing_quality": 0.9
            },
            "vision": {
              "planning_horizon_turns": 0.6,
              "weight_monopoly": 0.9,
              "weight_origin_bonus": 0.5,
              "weight_permission": 0.2,
              "weight_port": 0.5,
              "weight_toll": 0.2
            }
          },
          "skill": {
            "combo_awareness": 0.9,
            "description": "Perfil confiavel para jogo padrao. Comete menos oscilacoes, respeita melhor caixa e enxerga combinacoes basicas com consistencia.",
            "evaluation_noise": 0,
            "foresight": 0.9,
            "id": "solido",
            "label": "Solido",
            "liquidity_discipline": 0.9,
            "timing_quality": 0.9
          },
          "skill_preset_id": "elite"
        },
        "bankrupt": false,
        "board_node_id": "chance-009",
        "cash": 1082,
        "cash_display": "$ 1.082",
        "color_hex": "#a855f7",
        "color_id": "purple",
        "coupons": [],
        "id": "cpu-5",
        "is_human": false,
        "last_roll": [
          1,
          3
        ],
        "location_code": null,
        "location_label": "Sorte / Reves",
        "monopoly_regions": [],
        "name": "Jogador 5",
        "needs_new_contract": false,
        "permissions": [
          {
            "accent": "#4C4C4C",
            "id": "oil",
            "kind": "oil",
            "mortgaged": false,
            "purchase_price": 2000,
            "text": "#FFFFFF",
            "title": "Petr\u00f3leo"
          }
        ],
        "property_codes": [
          "SHA",
          "DAK",
          "RIO"
        ],
        "ship_type": "oil",
        "ship_type_label": "Petr\u00f3leo",
        "skip_turns": 0,
        "status_label": "retoma na proxima"
      }
    ],
    "report": {
      "activeKey": "cash-by-turn",
      "milestones": [
        {
          "label": "Turno 05",
          "phase": "Fechamento da rodada",
          "players": [
            {
              "cash": 1593,
              "id": "human",
              "patrimony_total": 4323,
              "permission_count": 1,
              "property_count": 2,
              "title_count": 2,
              "toll_count": 0
            },
            {
              "cash": 1475,
              "id": "cpu-1",
              "patrimony_total": 3835,
              "permission_count": 1,
              "property_count": 1,
              "title_count": 1,
              "toll_count": 0
            },
            {
              "cash": 1215,
              "id": "cpu-2",
              "patrimony_total": 3985,
              "permission_count": 1,
              "property_count": 2,
              "title_count": 2,
              "toll_count": 0
            },
            {
              "cash": 2027,
              "id": "cpu-3",
              "patrimony_total": 4787,
              "permission_count": 1,
              "property_count": 2,
              "title_count": 2,
              "toll_count": 0
            },
            {
              "cash": 1969,
              "id": "cpu-4",
              "patrimony_total": 3969,
              "permission_count": 1,
              "property_count": 0,
              "title_count": 0,
              "toll_count": 0
            },
            {
              "cash": 2023,
              "id": "cpu-5",
              "patrimony_total": 4023,
              "permission_count": 1,
              "property_count": 0,
              "title_count": 0,
              "toll_count": 0
            }
          ],
          "turnNumber": 5
        },
        {
          "label": "Turno 10",
          "phase": "Fechamento da rodada",
          "players": [
            {
              "cash": 1654,
              "id": "human",
              "patrimony_total": 4384,
              "permission_count": 1,
              "property_count": 2,
              "title_count": 2,
              "toll_count": 0
            },
            {
              "cash": 1339,
              "id": "cpu-1",
              "patrimony_total": 4039,
              "permission_count": 1,
              "property_count": 2,
              "title_count": 2,
              "toll_count": 0
            },
            {
              "cash": 485,
              "id": "cpu-2",
              "patrimony_total": 4025,
              "permission_count": 1,
              "property_count": 4,
              "title_count": 4,
              "toll_count": 0
            },
            {
              "cash": 2364,
              "id": "cpu-3",
              "patrimony_total": 5414,
              "permission_count": 1,
              "property_count": 3,
              "title_count": 3,
              "toll_count": 0
            },
            {
              "cash": 2004,
              "id": "cpu-4",
              "patrimony_total": 4004,
              "permission_count": 1,
              "property_count": 0,
              "title_count": 0,
              "toll_count": 0
            },
            {
              "cash": 1806,
              "id": "cpu-5",
              "patrimony_total": 4286,
              "permission_count": 1,
              "property_count": 1,
              "title_count": 1,
              "toll_count": 0
            }
          ],
          "turnNumber": 10
        },
        {
          "label": "Turno 20",
          "phase": "Fechamento da rodada",
          "players": [
            {
              "cash": 1209,
              "id": "human",
              "patrimony_total": 4389,
              "permission_count": 1,
              "property_count": 3,
              "title_count": 3,
              "toll_count": 0
            },
            {
              "cash": 778,
              "id": "cpu-1",
              "patrimony_total": 4228,
              "permission_count": 1,
              "property_count": 4,
              "title_count": 4,
              "toll_count": 0
            },
            {
              "cash": 783,
              "id": "cpu-2",
              "patrimony_total": 4323,
              "permission_count": 1,
              "property_count": 4,
              "title_count": 4,
              "toll_count": 0
            },
            {
              "cash": 2521,
              "id": "cpu-3",
              "patrimony_total": 5621,
              "permission_count": 1,
              "property_count": 3,
              "title_count": 3,
              "toll_count": 0
            },
            {
              "cash": 2054,
              "id": "cpu-4",
              "patrimony_total": 4054,
              "permission_count": 1,
              "property_count": 0,
              "title_count": 0,
              "toll_count": 0
            },
            {
              "cash": 1354,
              "id": "cpu-5",
              "patrimony_total": 4174,
              "permission_count": 1,
              "property_count": 2,
              "title_count": 2,
              "toll_count": 0
            }
          ],
          "turnNumber": 20
        }
      ]
    },
    "robot_skills": {
      "cpu-1": {
        "archetype_id": "balanced_trader",
        "manual_profile": true,
        "name": "Jogador 1",
        "profile_id": "balanced_trader",
        "profile_label": "Equilibrado",
        "skill": {
          "combo_awareness": 0.9,
          "description": "Perfil confiavel para jogo padrao. Comete menos oscilacoes, respeita melhor caixa e enxerga combinacoes basicas com consistencia.",
          "evaluation_noise": 0,
          "foresight": 0.9,
          "id": "solido",
          "label": "Solido",
          "liquidity_discipline": 0.9,
          "timing_quality": 0.9
        },
        "skill_preset_id": "elite"
      },
      "cpu-2": {
        "archetype_id": "balanced_trader",
        "manual_profile": true,
        "name": "Jogador 2",
        "profile_id": "balanced_trader",
        "profile_label": "Equilibrado",
        "skill": {
          "combo_awareness": 0.9,
          "description": "Perfil confiavel para jogo padrao. Comete menos oscilacoes, respeita melhor caixa e enxerga combinacoes basicas com consistencia.",
          "evaluation_noise": 0,
          "foresight": 0.9,
          "id": "solido",
          "label": "Solido",
          "liquidity_discipline": 0.9,
          "timing_quality": 0.9
        },
        "skill_preset_id": "elite"
      },
      "cpu-3": {
        "archetype_id": "balanced_trader",
        "manual_profile": true,
        "name": "Jogador 3",
        "profile_id": "balanced_trader",
        "profile_label": "Equilibrado",
        "skill": {
          "combo_awareness": 0.9,
          "description": "Perfil confiavel para jogo padrao. Comete menos oscilacoes, respeita melhor caixa e enxerga combinacoes basicas com consistencia.",
          "evaluation_noise": 0,
          "foresight": 0.9,
          "id": "solido",
          "label": "Solido",
          "liquidity_discipline": 0.9,
          "timing_quality": 0.9
        },
        "skill_preset_id": "elite"
      },
      "cpu-4": {
        "archetype_id": "balanced_trader",
        "manual_profile": true,
        "name": "Jogador 4",
        "profile_id": "balanced_trader",
        "profile_label": "Equilibrado",
        "skill": {
          "combo_awareness": 0.9,
          "description": "Perfil confiavel para jogo padrao. Comete menos oscilacoes, respeita melhor caixa e enxerga combinacoes basicas com consistencia.",
          "evaluation_noise": 0,
          "foresight": 0.9,
          "id": "solido",
          "label": "Solido",
          "liquidity_discipline": 0.9,
          "timing_quality": 0.9
        },
        "skill_preset_id": "elite"
      },
      "cpu-5": {
        "archetype_id": "balanced_trader",
        "manual_profile": true,
        "name": "Jogador 5",
        "profile_id": "balanced_trader",
        "profile_label": "Equilibrado",
        "skill": {
          "combo_awareness": 0.9,
          "description": "Perfil confiavel para jogo padrao. Comete menos oscilacoes, respeita melhor caixa e enxerga combinacoes basicas com consistencia.",
          "evaluation_noise": 0,
          "foresight": 0.9,
          "id": "solido",
          "label": "Solido",
          "liquidity_discipline": 0.9,
          "timing_quality": 0.9
        },
        "skill_preset_id": "elite"
      }
    },
    "schema": "rdm-ui-save-v1",
    "session": {
      "action_label": "Jogador 3: navio em movimento",
      "active_player_id": "cpu-3",
      "dice": [
        5,
        1
      ],
      "note": "O navio vai percorrer 6 casas no menor caminho ate NYC, passando por USH.",
      "phase": "Turno 26",
      "turn_label": "Turno 26",
      "turn_number": 26
    },
    "setup_defaults": {
      "ai_advanced_profiles": true,
      "ai_difficulty": "normal",
      "ai_manual_profiles": [
        "balanced_trader",
        "balanced_trader",
        "balanced_trader",
        "balanced_trader",
        "balanced_trader"
      ],
      "ai_manual_robot_configs": [
        {
          "archetypeId": "balanced_trader",
          "overrides": {
            "metadata": {
              "archetype_id": "balanced_trader",
              "negotiation_preset_id": "protetor",
              "personality_preset_id": "patrimonialista",
              "setup_archetype_id": "balanced_trader",
              "setup_customized": true,
              "skill_preset_id": "elite",
              "table_preset_id": "stage6_profile_table",
              "vision_preset_id": "foco_contrato"
            },
            "negotiation": {
              "buy_openness": 0.1,
              "desperation_discount": 0.2,
              "discount_tolerance": 0.1,
              "premium_tolerance": 0.7,
              "sell_openness": 0.1,
              "strategic_lock": 0.8
            },
            "personality": {
              "asset_attachment": 0.8,
              "cash_reserve_ratio": 0.3,
              "coupon_patience": 0.6,
              "description": "Mantem postura media entre protecao, ousadia e paciencia. Serve como referencia central para calibrar comportamento geral da mesa.",
              "id": "equilibrado",
              "impulsiveness": 0.2,
              "label": "Temperado",
              "risk_tolerance": 0.3
            },
            "skill": {
              "combo_awareness": 0.9,
              "evaluation_noise": 0,
              "foresight": 0.9,
              "liquidity_discipline": 0.9,
              "timing_quality": 0.9
            },
            "vision": {
              "planning_horizon_turns": 0.3,
              "weight_monopoly": 0.4,
              "weight_origin_bonus": 1,
              "weight_permission": 0.5,
              "weight_port": 0.8,
              "weight_toll": 0.1
            }
          }
        },
        {
          "archetypeId": "balanced_trader",
          "overrides": {
            "metadata": {
              "archetype_id": "balanced_trader",
              "negotiation_preset_id": "protetor",
              "personality_preset_id": "patrimonialista",
              "setup_archetype_id": "balanced_trader",
              "setup_customized": true,
              "skill_preset_id": "elite",
              "table_preset_id": "stage6_profile_table",
              "vision_preset_id": "foco_portos"
            },
            "negotiation": {
              "buy_openness": 0.1,
              "desperation_discount": 0.2,
              "discount_tolerance": 0.1,
              "premium_tolerance": 0.7,
              "sell_openness": 0.1,
              "strategic_lock": 0.8
            },
            "personality": {
              "asset_attachment": 0.8,
              "cash_reserve_ratio": 0.3,
              "coupon_patience": 0.6,
              "description": "Mantem postura media entre protecao, ousadia e paciencia. Serve como referencia central para calibrar comportamento geral da mesa.",
              "id": "equilibrado",
              "impulsiveness": 0.2,
              "label": "Temperado",
              "risk_tolerance": 0.3
            },
            "skill": {
              "combo_awareness": 0.9,
              "evaluation_noise": 0,
              "foresight": 0.9,
              "liquidity_discipline": 0.9,
              "timing_quality": 0.9
            },
            "vision": {
              "planning_horizon_turns": 0.1,
              "weight_monopoly": 0.2,
              "weight_origin_bonus": 0.9,
              "weight_permission": 0.3,
              "weight_port": 0.9,
              "weight_toll": 0.1
            }
          }
        },
        {
          "archetypeId": "balanced_trader",
          "overrides": {
            "metadata": {
              "archetype_id": "balanced_trader",
              "negotiation_preset_id": "protetor",
              "personality_preset_id": "patrimonialista",
              "setup_archetype_id": "balanced_trader",
              "setup_customized": true,
              "skill_preset_id": "elite",
              "table_preset_id": "stage6_profile_table",
              "vision_preset_id": "foco_malha"
            },
            "negotiation": {
              "buy_openness": 0.1,
              "desperation_discount": 0.2,
              "discount_tolerance": 0.1,
              "premium_tolerance": 0.7,
              "sell_openness": 0.1,
              "strategic_lock": 0.8
            },
            "personality": {
              "asset_attachment": 0.8,
              "cash_reserve_ratio": 0.3,
              "coupon_patience": 0.6,
              "description": "Mantem postura media entre protecao, ousadia e paciencia. Serve como referencia central para calibrar comportamento geral da mesa.",
              "id": "equilibrado",
              "impulsiveness": 0.2,
              "label": "Temperado",
              "risk_tolerance": 0.3
            },
            "skill": {
              "combo_awareness": 0.9,
              "evaluation_noise": 0,
              "foresight": 0.9,
              "liquidity_discipline": 0.9,
              "timing_quality": 0.9
            },
            "vision": {
              "planning_horizon_turns": 0.3,
              "weight_monopoly": 0.3,
              "weight_origin_bonus": 0.9,
              "weight_permission": 0.9,
              "weight_port": 0.7,
              "weight_toll": 0.1
            }
          }
        },
        {
          "archetypeId": "balanced_trader",
          "overrides": {
            "metadata": {
              "archetype_id": "balanced_trader",
              "negotiation_preset_id": "protetor",
              "personality_preset_id": "patrimonialista",
              "setup_archetype_id": "balanced_trader",
              "setup_customized": true,
              "skill_preset_id": "elite",
              "table_preset_id": "stage6_profile_table",
              "vision_preset_id": "foco_pedagios"
            },
            "negotiation": {
              "buy_openness": 0.1,
              "desperation_discount": 0.2,
              "discount_tolerance": 0.1,
              "premium_tolerance": 0.7,
              "sell_openness": 0.1,
              "strategic_lock": 0.8
            },
            "personality": {
              "asset_attachment": 0.8,
              "cash_reserve_ratio": 0.3,
              "coupon_patience": 0.6,
              "description": "Mantem postura media entre protecao, ousadia e paciencia. Serve como referencia central para calibrar comportamento geral da mesa.",
              "id": "equilibrado",
              "impulsiveness": 0.2,
              "label": "Temperado",
              "risk_tolerance": 0.3
            },
            "skill": {
              "combo_awareness": 0.9,
              "evaluation_noise": 0,
              "foresight": 0.9,
              "liquidity_discipline": 0.9,
              "timing_quality": 0.9
            },
            "vision": {
              "planning_horizon_turns": 0.5,
              "weight_monopoly": 0.2,
              "weight_origin_bonus": 0.2,
              "weight_permission": 0.3,
              "weight_port": 0.2,
              "weight_toll": 0.9
            }
          }
        },
        {
          "archetypeId": "balanced_trader",
          "overrides": {
            "metadata": {
              "archetype_id": "balanced_trader",
              "negotiation_preset_id": "protetor",
              "personality_preset_id": "patrimonialista",
              "setup_archetype_id": "balanced_trader",
              "setup_customized": true,
              "skill_preset_id": "elite",
              "table_preset_id": "stage6_profile_table",
              "vision_preset_id": "foco_monopolio"
            },
            "negotiation": {
              "buy_openness": 0.1,
              "desperation_discount": 0.2,
              "discount_tolerance": 0.1,
              "premium_tolerance": 0.7,
              "sell_openness": 0.1,
              "strategic_lock": 0.8
            },
            "personality": {
              "asset_attachment": 0.8,
              "cash_reserve_ratio": 0.3,
              "coupon_patience": 0.6,
              "description": "Mantem postura media entre protecao, ousadia e paciencia. Serve como referencia central para calibrar comportamento geral da mesa.",
              "id": "equilibrado",
              "impulsiveness": 0.2,
              "label": "Temperado",
              "risk_tolerance": 0.3
            },
            "skill": {
              "combo_awareness": 0.9,
              "evaluation_noise": 0,
              "foresight": 0.9,
              "liquidity_discipline": 0.9,
              "timing_quality": 0.9
            },
            "vision": {
              "planning_horizon_turns": 0.6,
              "weight_monopoly": 0.9,
              "weight_origin_bonus": 0.5,
              "weight_permission": 0.2,
              "weight_port": 0.5,
              "weight_toll": 0.2
            }
          }
        }
      ],
      "ai_profile_mode": "balanced",
      "ai_profile_order": [
        "balanced_trader"
      ],
      "company_name": "Minha Companhia",
      "human_color_id": "blue",
      "rival_count": 5
    }
  },
  "variant": "game-ai-ui-v2",
  "version": 1
}